hotfn/__init__.py
hotfn/http/__init__.py
hotfn/http/errors.py
hotfn/http/request.py
hotfn/http/response.py
hotfn/http/worker.py
hotfn/tests/__init__.py
hotfn/tests/data.py
hotfn/tests/test_request_parser.py
hotfn-0.0.6.dist-info/DESCRIPTION.rst
hotfn-0.0.6.dist-info/METADATA
hotfn-0.0.6.dist-info/RECORD
hotfn-0.0.6.dist-info/WHEEL
hotfn-0.0.6.dist-info/metadata.json
hotfn-0.0.6.dist-info/pbr.json
hotfn-0.0.6.dist-info/top_level.txt
