Metadata-Version: 2.0
Name: hotfn
Version: 0.0.6
Summary: Library to provide HTTP over STDIN/STDOUT
Home-page: https://github.com/denismakogon/hotfn-py
Author: Denis Makogon
Author-email: lildee1991@gmail.com
License: UNKNOWN
Platform: UNKNOWN
Classifier: Intended Audience :: Information Technology
Classifier: Intended Audience :: System Administrators
Classifier: License :: OSI Approved :: Apache Software License
Classifier: Operating System :: POSIX :: Linux
Classifier: Programming Language :: Python
Classifier: Programming Language :: Python :: 3
Classifier: Programming Language :: Python :: 3.5
Classifier: Programming Language :: Python :: 3.6
Requires-Dist: pbr (!=2.1.0,>=2.0.0)
